bandsplit_tensorflow/__init__.py
bandsplit_tensorflow/bandsplit_layer.py
bandsplit_tensorflow-0.1.2.dist-info/LICENSE
bandsplit_tensorflow-0.1.2.dist-info/METADATA
bandsplit_tensorflow-0.1.2.dist-info/WHEEL
bandsplit_tensorflow-0.1.2.dist-info/top_level.txt
bandsplit_tensorflow-0.1.2.dist-info/RECORD
