Metadata-Version: 2.1
Name: bandsplit_tensorflow
Version: 0.1.2
Summary: A non-official implementation of the BandSplit technique as a TensorFlow layer.
Home-page: https://github.com/narrietal/bandsplit_tensorflow
Author: Nicolas Arrieta Larraza
Author-email: n.arrieta.larraza@gmail.com
Classifier: Programming Language :: Python :: 3
Classifier: License :: OSI Approved :: MIT License
Classifier: Operating System :: OS Independent
Requires-Python: >=3.6
License-File: LICENSE
Requires-Dist: tensorflow >=2.0.0
